LICENSE
MANIFEST.in
NEWS
README.md
setup.py
Sparked.egg-info/PKG-INFO
Sparked.egg-info/SOURCES.txt
Sparked.egg-info/dependency_links.txt
Sparked.egg-info/requires.txt
Sparked.egg-info/top_level.txt
bin/sparkd
doc/sparkd.1
doc/api/class-tree.html
doc/api/frames.html
doc/api/help.html
doc/api/identifier-index.html
doc/api/index.html
doc/api/module-tree.html
doc/api/redirect.html
doc/api/sparked-module.html
doc/api/sparked-pysrc.html
doc/api/sparked.application-module.html
doc/api/sparked.application-pysrc.html
doc/api/sparked.application.Application-class.html
doc/api/sparked.application.Options-class.html
doc/api/sparked.application.StateMachine-class.html
doc/api/sparked.events-module.html
doc/api/sparked.events-pysrc.html
doc/api/sparked.events.EventDispatcher-class.html
doc/api/sparked.graphics-module.html
doc/api/sparked.graphics-pysrc.html
doc/api/sparked.graphics.stage-module.html
doc/api/sparked.graphics.stage-pysrc.html
doc/api/sparked.graphics.stage.Stage-class.html
doc/api/sparked.graphics.util-module.html
doc/api/sparked.graphics.util-pysrc.html
doc/api/sparked.gui-module.html
doc/api/sparked.gui-pysrc.html
doc/api/sparked.gui.MonitorWidget-class.html
doc/api/sparked.gui.StatusWindow-class.html
doc/api/sparked.hardware-module.html
doc/api/sparked.hardware-pysrc.html
doc/api/sparked.hardware.hal-module.html
doc/api/sparked.hardware.hal-pysrc.html
doc/api/sparked.hardware.hal.HardwareMonitor-class.html
doc/api/sparked.hardware.inputevent-module.html
doc/api/sparked.hardware.inputevent-pysrc.html
doc/api/sparked.hardware.inputevent.InputEvent-class.html
doc/api/sparked.hardware.inputevent.InputEventDevice-class.html
doc/api/sparked.hardware.inputevent.InputEventProtocol-class.html
doc/api/sparked.hardware.network-module.html
doc/api/sparked.hardware.network-pysrc.html
doc/api/sparked.hardware.network.NetworkConnectionService-class.html
doc/api/sparked.hardware.network.NetworkWebConnectionService-class.html
doc/api/sparked.hardware.power-module.html
doc/api/sparked.hardware.power-pysrc.html
doc/api/sparked.hardware.power.PowerService-class.html
doc/api/sparked.hardware.rfid-module.html
