Metadata-Version: 1.0
Name: Sparked
Version: 0.15
Summary: Application development framework for interactive installations
Home-page: http://scherpenisse.net/sparked
Author: Arjan Scherpenisse
Author-email: arjan@scherpenisse.net
License: MIT/X
Platform: UNKNOWN
Classifier: Framework :: Twisted
Classifier: Intended Audience :: Developers
Classifier: License :: OSI Approved :: MIT License
Classifier: Programming Language :: Python
Classifier: Topic :: Communications
Classifier: Topic :: Software Development :: Libraries :: Python Modules
Classifier: Topic :: Utilities
